flymyai/__init__.py
flymyai/core/__init__.py
flymyai/core/_client.py
flymyai/core/_response.py
flymyai/core/_response_factory.py
flymyai/core/_streaming.py
flymyai/core/authorizations.py
flymyai/core/client.py
flymyai/core/exceptions.py
flymyai/core/models.py
flymyai/multipart/__init__.py
flymyai/multipart/base_field.py
flymyai/multipart/binary_field.py
flymyai/multipart/payload.py
flymyai/multipart/simple_field.py
flymyai/utils/__init__.py
flymyai/utils/utils.py
flymyai_client-0.1.3.dist-info/METADATA
flymyai_client-0.1.3.dist-info/WHEEL
flymyai_client-0.1.3.dist-info/RECORD
