Metadata-Version: 2.1
Name: flymyai-client
Version: 0.1.3
Summary: 
Author: D1-3105
Author-email: lyerhd@gmail.com
Requires-Python: >=3.10,<4.0
Classifier: Programming Language :: Python :: 3
Classifier: Programming Language :: Python :: 3.10
Classifier: Programming Language :: Python :: 3.11
Classifier: Programming Language :: Python :: 3.12
Requires-Dist: httpx[http2] (>=0.26.0,<0.27.0)
Requires-Dist: pydantic (>=2.5.2,<3.0.0)
Requires-Dist: typing-extensions (>=4.9.0,<5.0.0)
